easy_equities_client/__init__.py
easy_equities_client/accounts/__init__.py
easy_equities_client/accounts/clients.py
easy_equities_client/accounts/parsers.py
easy_equities_client/accounts/types.py
easy_equities_client/clients.py
easy_equities_client/constants.py
easy_equities_client/instruments/__init__.py
easy_equities_client/instruments/clients.py
easy_equities_client/instruments/types.py
easy_equities_client/types.py
easy_equities_client/utils/__init__.py
easy_equities_client/utils/dataclasses.py
easy_equities_client-0.5.0.dist-info/LICENSE.txt
easy_equities_client-0.5.0.dist-info/WHEEL
easy_equities_client-0.5.0.dist-info/METADATA
easy_equities_client-0.5.0.dist-info/RECORD
