Metadata-Version: 2.1
Name: easy-equities-client
Version: 0.5.0
Summary: Unofficial Easy Equities and Satrix Python Client
Home-page: https://github.com/delenamalan/easy-equities-client
License: MIT
Keywords: easyequities,satrix,money
Author: Delena Malan
Author-email: delena.malan@gmail.com
Maintainer: Delena Malan
Maintainer-email: delena.malan@gmail.com
Requires-Python: >=3.6.1,<4
Classifier: Development Status :: 3 - Alpha
Classifier: Intended Audience :: Developers
Classifier: License :: OSI Approved :: MIT License
Classifier: Natural Language :: English
Classifier: Programming Language :: Python :: 3
Classifier: Programming Language :: Python :: 3.10
Classifier: Programming Language :: Python :: 3.6
Classifier: Programming Language :: Python :: 3.7
Classifier: Programming Language :: Python :: 3.8
Classifier: Programming Language :: Python :: 3.9
Requires-Dist: bs4 (>=0.0.1,<0.0.2)
Requires-Dist: dataclasses (>=0.8.0,<0.9.0); python_version < "3.7"
Requires-Dist: importlib-metadata (>=4.6.3,<5.0.0); python_version < "3.8"
Requires-Dist: requests (>=2.25.0,<3.0.0)
Requires-Dist: typing-extensions (>=3.10.0,<4.0.0); python_version < "3.8"
Project-URL: Repository, https://github.com/delenamalan/easy-equities-client
